tritopic/__init__.py
tritopic/core/__init__.py
tritopic/core/clustering.py
tritopic/core/embeddings.py
tritopic/core/graph_builder.py
tritopic/core/keywords.py
tritopic/core/model.py
tritopic/labeling/__init__.py
tritopic/labeling/llm_labeler.py
tritopic/utils/__init__.py
tritopic/utils/metrics.py
tritopic/visualization/__init__.py
tritopic/visualization/plotter.py
tritopic-0.1.0.dist-info/licenses/LICENSE
tritopic-0.1.0.dist-info/METADATA
tritopic-0.1.0.dist-info/WHEEL
tritopic-0.1.0.dist-info/top_level.txt
tritopic-0.1.0.dist-info/RECORD
