Metadata-Version: 2.4
Name: tritopic
Version: 0.1.0
Summary: Tri-Modal Graph Topic Modeling with Iterative Refinement - A state-of-the-art topic modeling library
Author-email: Roman Egger <roman@example.com>
License: MIT
Project-URL: Homepage, https://github.com/roman-egger/tritopic
Project-URL: Documentation, https://tritopic.readthedocs.io
Project-URL: Repository, https://github.com/roman-egger/tritopic
Keywords: topic-modeling,nlp,machine-learning,graph-clustering,leiden,embeddings,text-analysis,bertopic-alternative
Classifier: Development Status :: 4 - Beta
Classifier: Intended Audience :: Science/Research
Classifier: License :: OSI Approved :: MIT License
Classifier: Programming Language :: Python :: 3
Classifier: Programming Language :: Python :: 3.9
Classifier: Programming Language :: Python :: 3.10
Classifier: Programming Language :: Python :: 3.11
Classifier: Programming Language :: Python :: 3.12
Classifier: Topic :: Scientific/Engineering :: Artificial Intelligence
Classifier: Topic :: Text Processing :: Linguistic
Requires-Python: >=3.9
License-File: LICENSE
Requires-Dist: numpy>=1.21.0
Requires-Dist: pandas>=1.3.0
Requires-Dist: scipy>=1.7.0
Requires-Dist: scikit-learn>=1.0.0
Requires-Dist: sentence-transformers>=2.2.0
Requires-Dist: leidenalg>=0.9.0
Requires-Dist: igraph>=0.10.0
Requires-Dist: umap-learn>=0.5.0
Requires-Dist: hdbscan>=0.8.0
Requires-Dist: plotly>=5.0.0
Requires-Dist: tqdm>=4.60.0
Requires-Dist: rank-bm25>=0.2.0
Requires-Dist: keybert>=0.7.0
Provides-Extra: llm
Requires-Dist: anthropic>=0.18.0; extra == "llm"
Requires-Dist: openai>=1.0.0; extra == "llm"
Provides-Extra: full
Requires-Dist: anthropic>=0.18.0; extra == "full"
Requires-Dist: openai>=1.0.0; extra == "full"
Requires-Dist: pacmap>=0.6.0; extra == "full"
Requires-Dist: datamapplot>=0.1.0; extra == "full"
Provides-Extra: dev
Requires-Dist: pytest>=7.0.0; extra == "dev"
Requires-Dist: pytest-cov>=4.0.0; extra == "dev"
Requires-Dist: black>=23.0.0; extra == "dev"
Requires-Dist: ruff>=0.1.0; extra == "dev"
Requires-Dist: mypy>=1.0.0; extra == "dev"
Dynamic: license-file
